[
  {
    "name": "White Whale",
    "ticker": "WHITEWHALE",
    "chain_id": "solana",
    "pair_address": "4qxSqMh6iEdbdvtMp8r5MK2psAGKNk57PfGeVo2VhczQ",
    "project_id": "4qxSqMh6iEdbdvtMp8r5MK2psAGKNk57PfGeVo2VhczQ",
    "image_url": "images/whitewhale-card.png",
    "chart_url": "https://dexscreener.com/solana/4qxSqMh6iEdbdvtMp8r5MK2psAGKNk57PfGeVo2VhczQ",
    "badge_label": "gold",
    "badge_image": "images/badge-gold.png",
    "is_featured": true,
    "promo_rank": 1
  },
  {
  "name": "Discovery Mode",
  "ticker": "",
  "project_id": "system_discovery_mode",
  "pair_address": "system_discovery_mode",
  "image_url": "images/discovery-mode-card.PNG",
  "chart_url": "#",
  "badge_label": "gold",
  "badge_image": "images/badge-gold.png",
  "is_featured": true,
  "promo_rank": 999,
  "is_system_card": true,
  "system_card_type": "discovery_transition"
}
]
